CHANGES.rst
LICENSE
MANIFEST.in
README.rst
setup.py
lshashpy3/__init__.py
lshashpy3/lshash.py
lshashpy3/storage.py
lshashpy3.egg-info/PKG-INFO
lshashpy3.egg-info/SOURCES.txt
lshashpy3.egg-info/dependency_links.txt
lshashpy3.egg-info/requires.txt
lshashpy3.egg-info/top_level.txt