Metadata-Version: 2.1
Name: lshashpy3
Version: 0.0.9
Summary: A fast Python 3 implementation of locality sensitive hashing with persistance support.
Home-page: https://github.com/loretoparisi/lshash
Author: Kay Zhu
Author-email: me@kayzhu.com
Maintainer: Loreto Parisi
Maintainer-email: loretoparisi@gmail.com
License: MIT License
Platform: UNKNOWN
Classifier: Intended Audience :: Developers
Classifier: License :: OSI Approved :: MIT License
Classifier: Operating System :: OS Independent
Classifier: Programming Language :: Python
Classifier: Programming Language :: Python :: 3
Classifier: Topic :: Software Development :: Libraries
